json_lineage/__init__.py
json_lineage/__main__.py
json_lineage/bin_interface.py
json_lineage/cli.py
json_lineage/exceptions.py
json_lineage/public.py
json_lineage/bin/jsonl_converter
json_lineage/bin/jsonl_converter.exe
json_lineage/bin/tmp.py
json_lineage-0.2.2.dist-info/METADATA
json_lineage-0.2.2.dist-info/WHEEL
json_lineage-0.2.2.dist-info/top_level.txt
json_lineage-0.2.2.dist-info/RECORD
