Metadata-Version: 2.1
Name: json-lineage
Version: 0.2.2
Summary: Library to parse JSON files iteratively without loading the whole file into memory
Home-page: https://github.com/Salaah01/json-lineage
Author: "Salaah Amin"
License: "MIT"
Classifier: Development Status :: 5 - Production/Stable
Classifier: Intended Audience :: Developers
Classifier: License :: OSI Approved :: MIT License
Classifier: Programming Language :: Python :: 3
Classifier: Programming Language :: Python :: 3.7
Classifier: Programming Language :: Python :: 3.8
Classifier: Programming Language :: Python :: 3.9
Classifier: Programming Language :: Python :: 3.10
Classifier: Programming Language :: Python :: 3.11
Classifier: Programming Language :: Python :: 3.12
Classifier: Operating System :: OS Independent
Classifier: Topic :: Software Development :: Libraries :: Python Modules
Classifier: Topic :: File Formats :: JSON
Requires-Python: >=3.7
